pytest_nunit/__init__.py
pytest_nunit/attrs2xml.py
pytest_nunit/nunit.py
pytest_nunit/plugin.py
pytest_nunit/models/__init__.py
pytest_nunit/models/nunit.py
pytest_nunit-1.0.3.dist-info/LICENSE
pytest_nunit-1.0.3.dist-info/METADATA
pytest_nunit-1.0.3.dist-info/WHEEL
pytest_nunit-1.0.3.dist-info/entry_points.txt
pytest_nunit-1.0.3.dist-info/top_level.txt
pytest_nunit-1.0.3.dist-info/RECORD
