Metadata-Version: 2.1
Name: pytest-nunit
Version: 1.0.3
Summary: A pytest plugin for generating NUnit3 test result XML output
Home-page: https://github.com/pytest-dev/pytest-nunit
Author: Anthony Shaw
Author-email: anthonyshaw@apache.org
Maintainer: Anthony Shaw
Maintainer-email: anthonyshaw@apache.org
License: MIT License
Platform: UNKNOWN
Classifier: Development Status :: 5 - Production/Stable
Classifier: Framework :: Pytest
Classifier: Intended Audience :: Developers
Classifier: Topic :: Software Development :: Testing
Classifier: Programming Language :: Python
Classifier: Programming Language :: Python :: 2
Classifier: Programming Language :: Python :: 2.7
Classifier: Programming Language :: Python :: 3
Classifier: Programming Language :: Python :: 3.5
Classifier: Programming Language :: Python :: 3.6
Classifier: Programming Language :: Python :: 3.7
Classifier: Programming Language :: Python :: 3.8
Classifier: Programming Language :: Python :: 3.9
Classifier: Programming Language :: Python :: 3.10
Classifier: Programming Language :: Python :: 3.11
Classifier: Programming Language :: Python :: Implementation :: CPython
Classifier: Programming Language :: Python :: Implementation :: PyPy
Classifier: Operating System :: OS Independent
Classifier: License :: OSI Approved :: MIT License
Requires-Python: >=3.6
Requires-Dist: pytest (>=4.6.0)
Requires-Dist: attrs
Requires-Dist: enum34 (>=1.1.6) ; python_version=="2.7"
Provides-Extra: dev
Requires-Dist: xmlschema (==1.0.13) ; extra == 'dev'
Requires-Dist: pytest ; extra == 'dev'
Requires-Dist: pytest-cov ; extra == 'dev'
